gaaveregister/__init__.py
gaaveregister/admin.py
gaaveregister/apps.py
gaaveregister/models.py
gaaveregister/tests.py
gaaveregister/views.py
gaaveregister/migrations/__init__.py
medlemssys/__init__.py
medlemssys/urls.py
medlemssys/utils.py
medlemssys/aarsmelding/__init__.py
medlemssys/aarsmelding/models.py
medlemssys/aarsmelding/tests.py
medlemssys/aarsmelding/urls.py
medlemssys/aarsmelding/views.py
medlemssys/aarsmelding/templates/aarsmelding/index.html
medlemssys/aarsmelding/templates/aarsmelding/single.html
medlemssys/api/__init__.py
medlemssys/api/apps.py
medlemssys/api/serializers.py
medlemssys/api/tests.py
medlemssys/api/urls.py
medlemssys/api/views.py
medlemssys/behaviour/__init__.py
medlemssys/behaviour/barnogungdom.py
medlemssys/behaviour/base.py
medlemssys/config/__init__.py
medlemssys/config/urls.py
medlemssys/config/wsgi.py
medlemssys/config/settings/__init__.py
medlemssys/config/settings/common.py
medlemssys/config/settings/defaults.py
medlemssys/config/settings/local.py
medlemssys/contrib/__init__.py
medlemssys/giro/OCRB.ttf
medlemssys/giro/__init__.py
medlemssys/giro/admin.py
medlemssys/giro/admin_views.py
medlemssys/giro/models.py
medlemssys/giro/views.py
medlemssys/giro/migrations/0001_initial.py
medlemssys/giro/migrations/__init__.py
medlemssys/innhenting/__init__.py
medlemssys/innhenting/a.py
medlemssys/innhenting/mod10.py
medlemssys/innhenting/ocr.py
medlemssys/innhenting/views.py
medlemssys/innhenting/management/__init__.py
medlemssys/innhenting/management/nmu.py
medlemssys/innhenting/management/commands/__init__.py
medlemssys/innhenting/management/commands/medlem_import.py
medlemssys/innhenting/management/commands/ocr_import.py
medlemssys/innhenting/management/commands/postnr_bolstad_import.py
medlemssys/medlem/__init__.py
medlemssys/medlem/admin.py
medlemssys/medlem/admin_actions.py
medlemssys/medlem/behaviours.py
medlemssys/medlem/filters.py
medlemssys/medlem/forms.py
medlemssys-0.12.2.dist-info/METADATA
medlemssys-0.12.2.dist-info/RECORD
medlemssys-0.12.2.dist-info/WHEEL
medlemssys-0.12.2.dist-info/entry_points.txt
medlemssys-0.12.2.dist-info/top_level.txt
