Metadata-Version: 2.1
Name: medlemssys
Version: 0.12.2
Summary: Membership register for norwegian youth organizations
Home-page: https://github.com/odinho/medlemssys
Author: Odin Hørthe Omdal
Author-email: odin.omdal@gmail.com
License: AGPLv3+
Platform: UNKNOWN
Classifier: Development Status :: 4 - Beta
Classifier: Environment :: Web Environment
Classifier: Framework :: Django
Classifier: Intended Audience :: End Users/Desktop
Classifier: Intended Audience :: System Administrators
Classifier: License :: OSI Approved :: GNU Affero General Public License v3 or later (AGPLv3+)
Classifier: Operating System :: OS Independent
Classifier: Programming Language :: Python :: 2.7
Classifier: Topic :: Database :: Front-Ends
Classifier: Topic :: Office/Business
Provides-Extra: production
Requires-Dist: Django (<1.11,>=1.10)
Requires-Dist: logan
Requires-Dist: whitenoise
Requires-Dist: django-model-utils
Requires-Dist: pytz
Requires-Dist: reportlab
Requires-Dist: python-dateutil
Requires-Dist: djangorestframework (>=3.0)
Requires-Dist: django-reversion (>=2.0)
Requires-Dist: django-reversion-compare (>=0.8)
Provides-Extra: production
Requires-Dist: django-gunicorn; extra == 'production'
Requires-Dist: gunicorn; extra == 'production'
Requires-Dist: psycopg2; extra == 'production'
Requires-Dist: raven; extra == 'production'
